{
    "title": "ONIDA 215 L Direct Cool Single Door 2 Star Refrigerator  (Wine Lily, RDS2152P)",
    "product_specification": {
        "In The Box": "1 Unit Refrigerator, User Guide",
        "Type": "Single Door",
        "Refrigerator Type": "Top Freezer",
        "Defrosting Type": "Direct Cool",
        "Compressor Type": "Reciprocatory Compressor",
        "Capacity": "215 L",
        "Number of Doors": "1",
        "Star Rating": "2",
        "Coolpad": "No",
        "Toughened Glass": "Yes",
        "Built-in Stabilizer": "No",
        "Convertible Refrigerator": "No",
        "Shelf Material": "Toughened Glass",
        "Door Lock": "Yes",
        "Gasket Type": "Anti Bacterial",
        "Removable Gasket": "Yes",
        "Water & Ice Dispenser": "No",
        "Water Dispenser": "No",
        "Power Consumption": "114 W",
        "BEE Rating Year": "2020",
        "Stabilizer Required": "Yes",
        "Number of Freezer Shelves": "1",
        "Number of Freezer Drawers": "1",
        "Launch Year": "2020",
        "Net Total Capacity": "215 L",
        "Other Features": "Anti-Bacterial Removal Gasket, Jumbo Vege Box, Large Storage Space, Floral Design Door, Environment Friendly, Power Cut Evocool Technology",
        "Net Height": "1245 mm",
        "Net Depth": "665 mm",
        "Net Width": "540 mm",
        "Weight": "38.5 kg",
        "Installation & Demo": "This product does not require installation. The features of the product are presented in the user manual that comes with it. Hence, the manufacturer does not provide on-site installation or demo for the product. In case of any queries about the installation or the features of product, kindly call us at 1800 208 9898 or (080) 49400000 for assistance.",
        "Warranty Service Type": "Technician Visit",
        "Warranty Summary": "1 Year Comprehensive Warranty on Product, 10 Years Warranty on Compressor",
        "Covered in Warranty": "All Parts Excluding Plastic Parts, Glassware, Bulb and Tube from the Date of Purchase Against Defective Material and Workmanship",
        "Not Covered in Warranty": "Parts: Plastic / Glassware / Bulb / Tube. Any Accessories External to the Product. The Product is Not Used According to the Instructions Given in the Instructions Manual. Defects Caused by Improper Use as Determined by the Company Personnel. Modification or Alteration of Any Nature made in the Electrical Circuitry or Physical Construction of the Set. Site (Where the Premises is Kept) Conditions That do Not Confirm to the Recommended Operating Conditions of the Machine. The Serial Number is Removed, Altered or Obliterated from the Machine. Defects Due to Cause Beyond Control Like Lightening, Abnormal Voltage, Acts of God or While in Transit to the Service Centres or Purchasers Residence"
    },
    "product_description": {
        "Designer Floral Door": "This home appliance features an aesthetically pleasing designer floral door to add some style to your kitchen area.",
        "Antibacterial Removal Gasket": "This gasket keeps the door liner clean to keep your edibles hygienic and fresh. Also, it prevents bacteria and fungi from forming inside this refrigerator.",
        "": ""
    },
    "reviews": {
        "ratings": [
            "5",
            "2",
            "4",
            "4",
            "5",
            "5",
            "5",
            "5",
            "5",
            "5",
            "5",
            "2",
            "4",
            "4",
            "5",
            "5",
            "5",
            "5",
            "5",
            "5",
            "4",
            "5",
            "5",
            "5",
            "5",
            "4",
            "3",
            "5",
            "4",
            "4",
            "5",
            "1",
            "5",
            "5",
            "5",
            "5",
            "4",
            "1",
            "5",
            "5",
            "4",
            "5",
            "4",
            "5",
            "5",
            "5",
            "5",
            "5",
            "3",
            "4",
            "5",
            "4",
            "4",
            "5",
            "4",
            "5",
            "5",
            "2",
            "1",
            "4",
            "5",
            "5",
            "5",
            "4",
            "5",
            "4",
            "5",
            "4",
            "1",
            "5",
            "5",
            "5",
            "5",
            "1",
            "5",
            "3",
            "4",
            "5",
            "5",
            "5",
            "1",
            "5",
            "1",
            "1",
            "1",
            "5",
            "5",
            "1",
            "5",
            "1",
            "1",
            "1",
            "5",
            "5",
            "1",
            "1",
            "5",
            "2",
            "4",
            "4",
            "5",
            "3",
            "2",
            "5",
            "5",
            "5",
            "5",
            "5",
            "5",
            "2",
            "4",
            "1",
            "1",
            "4",
            "5",
            "4",
            "5",
            "4",
            "4",
            "5",
            "5",
            "5",
            "1",
            "5",
            "5",
            "1",
            "4",
            "5",
            "3",
            "5",
            "4",
            "5",
            "1",
            "5",
            "5",
            "1",
            "5",
            "5",
            "3",
            "4",
            "4",
            "4",
            "4",
            "4",
            "5",
            "3",
            "5",
            "5",
            "5",
            "1",
            "3",
            "5",
            "5",
            "4",
            "4",
            "1",
            "2",
            "5",
            "5",
            "4",
            "4",
            "5",
            "5",
            "5",
            "5",
            "5",
            "3",
            "4",
            "5",
            "3",
            "3",
            "4",
            "5",
            "5",
            "1",
            "5",
            "5",
            "4",
            "3",
            "4",
            "1",
            "5",
            "5",
            "5",
            "5",
            "5",
            "5",
            "5",
            "1",
            "3",
            "3",
            "5",
            "4",
            "5",
            "5",
            "3",
            "3",
            "5",
            "4",
            "5",
            "5",
            "4",
            "5",
            "5",
            "4",
            "5",
            "4",
            "5",
            "5",
            "5",
            "5",
            "5",
            "4",
            "1",
            "5",
            "5",
            "3",
            "4",
            "3",
            "3",
            "5",
            "4",
            "3",
            "5",
            "5",
            "3",
            "4",
            "5",
            "4",
            "4",
            "5",
            "5",
            "5",
            "5",
            "4",
            "5",
            "5",
            "3",
            "5",
            "4",
            "5",
            "4",
            "2",
            "4",
            "3",
            "4",
            "3",
            "5",
            "5",
            "3",
            "5",
            "4",
            "5",
            "5",
            "5",
            "4",
            "5",
            "1",
            "5",
            "5",
            "5",
            "4",
            "4",
            "1",
            "5",
            "5",
            "5",
            "5",
            "5",
            "5",
            "4",
            "5",
            "5",
            "5",
            "4",
            "1",
            "5",
            "3",
            "4",
            "5",
            "3",
            "3",
            "5",
            "4",
            "5",
            "1",
            "5",
            "5",
            "4",
            "5",
            "5",
            "4",
            "4",
            "5",
            "5",
            "5",
            "4",
            "3",
            "5",
            "5",
            "5",
            "4",
            "3",
            "5",
            "5",
            "5",
            "3",
            "5",
            "3",
            "5",
            "5",
            "1",
            "5",
            "4",
            "4",
            "5",
            "4",
            "1",
            "5",
            "4",
            "5",
            "3",
            "5",
            "5",
            "5",
            "5",
            "4",
            "5",
            "5",
            "5",
            "4",
            "5",
            "4",
            "5",
            "5",
            "5",
            "4",
            "5",
            "5",
            "5",
            "5",
            "4",
            "5",
            "5",
            "4",
            "4",
            "5",
            "5",
            "4",
            "5",
            "5",
            "5",
            "4",
            "5",
            "3",
            "4",
            "4",
            "3",
            "5",
            "5",
            "5",
            "5",
            "2",
            "3",
            "3",
            "5",
            "2",
            "5",
            "4",
            "5",
            "3",
            "5",
            "5",
            "5",
            "3",
            "5",
            "5",
            "5",
            "1",
            "4",
            "1",
            "1",
            "5",
            "1",
            "5",
            "5",
            "4",
            "5",
            "5",
            "5",
            "4",
            "5",
            "5",
            "5",
            "4",
            "5",
            "5",
            "4",
            "5",
            "4",
            "4",
            "4",
            "3",
            "4",
            "5",
            "5",
            "4",
            "3",
            "5",
            "1",
            "5",
            "4",
            "5",
            "4",
            "5",
            "5",
            "5",
            "5",
            "4",
            "5",
            "4",
            "5",
            "5",
            "5",
            "5",
            "5",
            "5",
            "4",
            "4",
            "4",
            "4",
            "5",
            "4",
            "2",
            "5",
            "5",
            "5",
            "4",
            "5",
            "4",
            "4",
            "5",
            "5",
            "1",
            "3",
            "5",
            "5",
            "4",
            "3",
            "4",
            "4",
            "5",
            "1",
            "5",
            "3",
            "4",
            "5",
            "5",
            "5",
            "4",
            "3",
            "5",
            "5",
            "4",
            "4",
            "5",
            "3",
            "5",
            "4",
            "5",
            "5",
            "5",
            "5",
            "4",
            "5",
            "4",
            "5",
            "5",
            "3",
            "5",
            "5",
            "5",
            "4",
            "5",
            "4",
            "5",
            "5",
            "3",
            "5",
            "5",
            "3",
            "5",
            "5",
            "4",
            "5",
            "4",
            "3",
            "5",
            "5",
            "4",
            "5",
            "5",
            "3",
            "5",
            "3",
            "5",
            "5",
            "5",
            "5",
            "5",
            "5",
            "5",
            "5",
            "3",
            "5",
            "4",
            "4",
            "1",
            "4",
            "1",
            "5",
            "4",
            "5",
            "4",
            "5",
            "5",
            "5",
            "5",
            "5",
            "4",
            "5",
            "4",
            "5",
            "5",
            "5",
            "4",
            "4",
            "1",
            "3",
            "2",
            "5",
            "4",
            "4",
            "1",
            "4",
            "5",
            "4",
            "5",
            "4",
            "3",
            "1",
            "5",
            "1",
            "4",
            "5",
            "5",
            "5",
            "4",
            "5",
            "5",
            "4",
            "3",
            "5",
            "5",
            "1",
            "5",
            "5",
            "4",
            "4",
            "1",
            "3",
            "5",
            "3",
            "5",
            "5",
            "5",
            "4",
            "5",
            "3",
            "4",
            "5",
            "4",
            "3",
            "5",
            "5",
            "5",
            "4",
            "5",
            "4",
            "5",
            "2",
            "3",
            "5",
            "5",
            "5",
            "3",
            "3",
            "5",
            "5",
            "5",
            "5",
            "5",
            "5",
            "4",
            "4",
            "5",
            "5",
            "4",
            "4",
            "4",
            "5",
            "4",
            "4",
            "3",
            "5",
            "4",
            "5",
            "5",
            "5",
            "5",
            "5",
            "5",
            "5",
            "2",
            "5",
            "5",
            "5",
            "5",
            "5",
            "3",
            "5",
            "5",
            "5",
            "5",
            "5",
            "5",
            "5",
            "5",
            "3",
            "5",
            "5",
            "5",
            "5",
            "4",
            "4",
            "4",
            "1",
            "5",
            "1",
            "3",
            "4",
            "3",
            "5",
            "5",
            "4",
            "4",
            "5",
            "4",
            "3",
            "5",
            "5",
            "5",
            "3",
            "4",
            "5",
            "5",
            "5",
            "4",
            "2",
            "4",
            "5",
            "5",
            "1",
            "4",
            "4",
            "5",
            "5",
            "3",
            "5",
            "5",
            "2",
            "5",
            "5",
            "4",
            "5",
            "5",
            "5",
            "3",
            "5",
            "5",
            "5",
            "4",
            "4",
            "4",
            "5",
            "4",
            "3",
            "5",
            "5",
            "5",
            "4",
            "5",
            "4"
        ],
        "review": [
            "Awesome product. A very good refrigerator with lot of features like lnstant chilling, quick ice formation, Temperature control knob with atmospheric conditions and very good metalic body with floral designs.\nFinally it's worth for the money spent.",
            "Fridge parts are cheap, overall look wise good but finishing is not upto mark. Compressor making lot of noise. Overall not worth of money spend",
            "Very nice Design and Graphics at this price.... Very low Sound of the compressor..... Fast and efficient cooling which is very good.... Make & Built quality is very good.... Overall value for money product... Must buy for the price given after offers at Flipkart.....",
            "Everything was 5in but for installation n warranty clime is not available with the fridge so before buying this item from flipkart please do check all this n assure ur self that everything is 5in then u buy apart from all this everything is fine",
            "Appreciate the delivery boys who did fantastic job.. Though my area was under seal down..they did a great delivery.. Appreciate their hardwork,patience and commitment during these tough times..",
            "Very good product\nPerformance good\nIndian brand \ud83c\uddee\ud83c\uddf3",
            "NICE AND SMALL FRIDGE AND BODY IS FULLY METALIC . GOOD BACK SIDE FINISH",
            "Good product",
            "Awesome.... immediately chilling...Superb & nice floral design look ...must buy ONIDA REFRIGERATOR I AM FULLY SATISFIED.",
            "Superb design and nice performance,My suggestion to u this is prefect for small family or a newly couple .... thankyou \ud83d\ude0a",
            "Awesome product. A very good refrigerator with lot of features like lnstant chilling, quick ice formation, Temperature control knob with atmospheric conditions and very good metalic body with floral designs.\nFinally it's worth for the money spent.",
            "Fridge parts are cheap, overall look wise good but finishing is not upto mark. Compressor making lot of noise. Overall not worth of money spend",
            "Very nice Design and Graphics at this price.... Very low Sound of the compressor..... Fast and efficient cooling which is very good.... Make & Built quality is very good.... Overall value for money product... Must buy for the price given after offers at Flipkart.....",
            "Everything was 5in but for installation n warranty clime is not available with the fridge so before buying this item from flipkart please do check all this n assure ur self that everything is 5in then u buy apart from all this everything is fine",
            "Appreciate the delivery boys who did fantastic job.. Though my area was under seal down..they did a great delivery.. Appreciate their hardwork,patience and commitment during these tough times..",
            "Very good product\nPerformance good\nIndian brand \ud83c\uddee\ud83c\uddf3",
            "NICE AND SMALL FRIDGE AND BODY IS FULLY METALIC . GOOD BACK SIDE FINISH",
            "Good product",
            "Awesome.... immediately chilling...Superb & nice floral design look ...must buy ONIDA REFRIGERATOR I AM FULLY SATISFIED.",
            "Superb design and nice performance,My suggestion to u this is prefect for small family or a newly couple .... thankyou \ud83d\ude0a",
            "Good one. loved it.\nValue for money.",
            "Super design.. I love it",
            "Good item",
            "Good product.......",
            "Valu for money",
            "very good and nice product i will 2nd time purchased same item",
            "Nice product",
            "Thank you flipcart\ud83d\ude0d\ud83d\ude0d",
            "Super",
            "Good",
            "Always good...",
            "Don't buy this product hug sounds and customer care not support",
            "To good",
            "Awesome product, value for money \ud83e\udd70",
            "Best for the price range, been using it since 10days",
            "Medium range and Power Savar Fridge\nGood Storage..",
            "Sumall size but ok.... supper",
            "Not ok",
            "Good product for a small family within this price range. Recommend to buy.",
            "Very too good product. Then value for money really. I can not say what a great deal with Flipkart.",
            "It has 190 mention in the buying screen, however it has s\n180 liters capacity inside. Looks very small size. For small family it's good for them",
            "Dear, customers of flipkart, if u r looking for a low budget high performance & design/appearance similar to branded refrigerator in a low economic budget, then don't hesitate for a moment.\nThe fridge in this economic range, completely overcome the all requirements of a small/ medium family.\nDon't go through the negative reviews posted by others.",
            "Good product and value for money..",
            "Very valuable",
            "Superb",
            "Got it in 7500 in big billion days . Slightly sounds the compressor. Value for money, everything provided in this price.",
            "Nice product thank you Flipkart budget product...I will given gift to my grandmother....she very happy with color and design...",
            "Very good product.....",
            "Good Onida refrigerator",
            "Good for small family, great cooling in this budget",
            "Best product",
            "Delivered on time..Good for couples staying in rent house.... smaller than expected.but worth it...",
            "Value for money best refregerator thanks Flipkart",
            "Best Choice for Couple.... Value for Money....Nic Design also",
            "Superb",
            "Very good product, for vailue of money\ud83d\udcb0",
            "Product is awesome. But delivery is very slow. 15 day's late delivery.\ud83d\ude02\ud83d\ude02\ud83d\ude02",
            "No installation.. noisy..",
            "This product defeated",
            "Fast cooling",
            "Super",
            "Thanks to Flipkart, nice one before time delivered and delivery boy was very much helpful, product is value for money....",
            "Nice",
            "pros\n1.best cooling\n2. less noise from compressor\n3.LED lite placement\n4.floral design\n\ncons\n1.refrigerator size is small\n2. very small vegetable box\n3. body parts are made of cheap plastic\n\nverdict\nif u are newly married couple..and your budget is too short...then go ahead with this refrigerator without any second opinion",
            "good prodect",
            "Nice products & good for money value",
            "Good",
            "Gd one, really economy and effective product..",
            "It is sounding like an Oil engine, worst product pls don't buy. Pls, don't buy on Flipkart also.",
            "Very beuty full product in very lowest price thanku for flipcart delivery time is adject in ur home i prefer this fridge best to small family",
            "Good product",
            "Value for money and good for small family, sound is very smooth",
            "Better than other products.best cooing now, I give 4 star's for onida..\nThanks to delivery team and flipkart.",
            "Stop working in one month of delivery .\nAfter so many complain no one responding to fix it . They says we have informed technical team but no body came till yet .\nNot working from last -4-5 days . Very poor service . Never buy these brands",
            "Very good product",
            "Pasting of stickeres quality is very poor. Compressor making heavy noise and looking very cheap",
            "Nice product love it",
            "It's a good product affordable price and refrigerators performance good. delivery time also good thanks flipkart team",
            "Good I'm happy with this product",
            "Nice product in low price",
            "Stand of the refrigerator was bent from back",
            "good product",
            "freezer stopped working after 3 months",
            "Very cheap product from India and flip card",
            "Very bad item never buy this product plz don't buy",
            "Best for money... performance is good... I like it..",
            "Nice product \u2764\ufe0f",
            "Very bad prodet",
            "Just purchased, delivery was good. Nice design for Small family, will review the performance later.. Worth buying so far..",
            "New refrigerator and light doesnt works...have logged 2 calls so far with Onida, flipkart but problem not solved yet.\n\nEven after one light is not fixed. New fridge and light not working.",
            "Refrigerator not working neither technician comes for installation. I have purchased for gift but filing very guilty",
            "Very Poor product",
            "Best in this range, loved it.",
            "It's very small in size but cooling was very instant......2 members family its very usefull",
            "The refrigirator surface is sweating water drops. Insulation is not proper. Noise is more.",
            "Worst ever product don't buy this for any reasons..",
            "Good",
            "This is the worst product you can ever have. It makes hell lot of noise within 10 days of its use.",
            "Although the working of fridge is excellent but during ordering Flipkart has accepted my old fridge exchange for a new one .\nRegardless of being of old fridge perfectly working with a little problem in the fridger section and little rust in the bottom ; they have not accepted my old fridge.\nIf they have to do this only ; they have not showed this criteria so that we could do something with the old fridge before ordering a new one. And now we have two fridges at home ; occupying a hell lot space.",
            "Small and Cute, Good For 2-3 People. Same like shown in Image. As this is first day, have to Check on Performance.",
            "nice fridge fast cooling",
            "Value for money. For small family and bachelor it's good for them. But finishing is not good at all.makes lots of noise. It's too much irritating",
            "Ordered first ...clamps on backside grill was broken\nRepalced the product and again got more faulty one\n4th leg is short compared to other legs .so it's shaking...have to keep paper under the leg to balance\nWire is very short..would suggest avoid the product",
            "Beautiful colour, body looks sturdy, very silent, product was packed and delivered well..worth the money",
            "I like this product",
            "Value for money and best thing Indian company",
            "worth money beautiful design I m very happy",
            "After one week use. Cooling is awesome, value for money segment.",
            "Best",
            "I think this is not 190 litre, it's very small,\n\nFilkart why you are cheating",
            "Good cooling but ice forming rate is high",
            "Quality is to bad",
            "Notice issue dore open automatically...don't buy this ... product..bakvas..and no replacement..",
            "Like it",
            "Very good product",
            "Nice product \ud83d\udc4c\ud83d\udc4c, Well packed, delivered in time at the door. Must buy #Fully Paisa wasool...",
            "Nice products",
            "Good \ud83d\ude0a",
            "simply Superb",
            "In Short : Its stylish and pocket friendly. Go for It.",
            "Good",
            "Excellent product in cheaper price. I am fully Seticfied.",
            "No demo or installation done and no one will come as well - this is horrible please",
            "Lovely product \ud83e\udd17\ud83e\udd17",
            "Good awesome",
            "Had a very bad experience buying this product..",
            "Very nice product \ud83d\udc4c",
            "Better than other products.best cooing now, I give 4 star's for onida..\nThanks to delivery team and flipkart.",
            "I can say not bad",
            "Super \ud83c\udf89\ud83c\udf89",
            "Nice",
            "Chilled",
            "worst product",
            "Beutifull",
            "Really good product",
            "Very cheap quality don't buy this small In size \ud83d\ude21",
            "Good",
            "Its a nice Refrigerator. Its compartments are good with All hard glass used. Design & blue color is really nice one. Happy with this fridge. Ther is no installation from company side so u hav to do it ur own. Overall nice product from onida. Recommended",
            "Ok",
            "Performance is good",
            "Ok",
            "I liked this refrigerator attractive floral blue design. It's very nice. I feel very happy for brought this refrigerator. Small disappointed because this refrigerator interior capacity only 180L. But outside showing 190L. Also this refrigerator is very small size. Small size family is more than better for this refrigerator.",
            "Good product",
            "Nice product",
            "Good",
            "Very good",
            "Ver good product as low price .. don't think just go for it",
            "Good luck",
            "Good in this price..",
            "Does not meet expectations",
            "Color is good but plate is glass and space is less",
            "Nice perfect",
            "Super",
            "Overall good product and value for money",
            "Product is very useful",
            "Fridge unwanted sound many times In a day Waste of money.",
            "Fridge not working properly all vegetables and fruits wastage",
            "Good Quality Product",
            "Value for money, it's most suitable for my office.",
            "Good",
            "Over nice item by Onida..\ud83e\udd17\ud83e\udd17",
            "Value for money",
            "Best quality and rate",
            "Thanks",
            "Good looks and prompt delivery....",
            "Nice",
            "Good",
            "Good",
            "Ok",
            "wonderful iteam",
            "Worth Buying it go for it, if you are looking for a budget refrigerator",
            "Good",
            "Best Products. Nice Experience.",
            "Best in the budget from a good company.",
            "Super product cooling is Asom",
            "Value for money",
            "Nice",
            "Value for money",
            "Good in this budget but compressor making noise",
            "supper",
            "Do not buy this product compressor getting much volume after one year using",
            "Good",
            "Good value for money product got @ 9290. Set winter mode and 0 noise of compressor. Fully recommended",
            "Good super",
            "Awesome",
            "Good",
            "Excellent product",
            "Thumbs-up",
            "Stop working in one month of delivery .\nAfter so many complain no one responding to fix it . They says we have informed technical team but no body came till yet .\nNot working from last -4-5 days . Very poor service . Never buy these brands",
            "This is very nice product .",
            "So much sound",
            "Nice",
            "Good",
            "Best product",
            "Good",
            "The first fridge I got was not cooling as it had some damage, it got delayed for the second fridge delivery However flipkart did good job in coordinating with manufacturer and now the second one I got is working fine",
            "Mackanice not present and do not set it",
            "good",
            "Good",
            "Good",
            "Nice",
            "Worth for money.",
            "Good looking\nGood space buy it blindly",
            "Very nice",
            "(My products is packing is very late i can wait one hour i am request to salsa boy & packing boy but his not support) only packing but product is excellent salsa boy showing in all products he is explain all products thank you\ud83d\ude4f",
            "Nice product\ud83e\udd70",
            "Ok",
            "Good One",
            "Awesome",
            "I'm really grateful for the deal. Purchased this at a good price",
            "Nice looking",
            "Super \u2764\ufe0f",
            "Good",
            "Not good",
            "Good",
            "good product",
            "Simply ossom",
            "Best product in cheapest price",
            "Not bad",
            "Worst products",
            "ONIDA 190 L Direct Cool Single Door 3 Star refrigerator is a best quality and performance.",
            "Good but initially it didn\u2019t sound much but it\u2019s been 4 months now it started noise a bit like old one but still nice electricity consumption even better than my other 4 star Samsung refrigerator..",
            "Too much icing in ice section so need to defrost regularly. Chiller tray is always disbalance. Rest is okay",
            "Value for Money",
            "Looking great, performance upto the mark, power consumption moderate, good product, value for money",
            "Worst fridge I have ever seen,bought on exchange of our good working fridge and we got this waste fridge. Don't even take a chance on buying this worst thing",
            "Good",
            "The product is very good",
            "It is ok",
            "Good Value for money",
            "Excellent",
            "Good product at reasonable price",
            "Very nice",
            "very goood",
            "Good",
            "Amazing item \u2764\ufe0f\u2764\ufe0f",
            "Excellent work",
            "Good",
            "Very beautiful product in Flipkart very cheap rate so nice product so carefully so helpful enjoy the fridge I am happy the fridge the text from the right away",
            "Overall it is good. Only concerned thing is that even at lowest mode it freezes things quickly.",
            "Very good refrigerator paisa vasool",
            "Thankyou",
            "West of money worest it was not working",
            "Good",
            "Good",
            "It's good...",
            "It's ok, but compare to others all trays are small one",
            "Excellent",
            "great product in this price segment",
            "Nice",
            "overall good",
            "Nice",
            "Fantastic",
            "Nice",
            "Excellent but making noise",
            "Awesome",
            "Nice fridge",
            "Cheap quality parts of the refrigerator.",
            "I had misunderstood a little ground but now chat pr understand me well",
            "Very good refrigerator in this price range\ud83d\ude0ai am realy impresed",
            "Super build quality products from Onida\nBelieve me buy this without hesitation this is the best one and quality product\nCooling 5/5\nDesign 5/5\nBuild quality 5/5\nSilent operation 5/5\n\nI haven't found and negative as of now\n25 days of usage",
            "Value for money ..good for small families",
            "Heavy sound motor",
            "N\nDon't buy this product it is so small it is less than 190 lit\nAnd this product is NO REUTEN\nWASTE",
            "Nice fridge within the budget.",
            "Aswm.. I like it in this budget",
            "Good refrigerator at this prize good value for money",
            "Amazing product. Worth buying.. \ud83d\ude42\ud83d\ude42",
            "Very nice",
            "Super refrigerator good condition I like it",
            "Good one at this price",
            "Good price",
            "Very nice",
            "It's a very good deal to get this fridge at 8300.. The fridge has depth instead of height to accommodate space and it's fairly good buy for small families.",
            "Ok",
            "It is very sad to say that don't buy this refrigerator.. Total wastage of money..Service is pathetic..",
            "Super not waste money\nExtraordinary \ud83d\udc8b",
            "Nice",
            "Best",
            "Good",
            "Not good but ok",
            "Original Colour of refrigerator is not good as it looks on flipcart",
            "VERY NICE PRODUCT IT'S COOL INSTANTLY",
            "Good",
            "Ok",
            "Within 15 days fridges got damaged not working no cooling there are lots of problem in fridge don't buy this worst no use of purchasing",
            "Nice value for money",
            "Super Product.........",
            "Good one as per money and quality point of view",
            "Nice product",
            "Wonderful \ud83d\ude0a\ud83d\ude0a im very happy with this purchase \ud83d\ude0d\ud83d\ude0d\ud83d\ude0d\ud83d\ude0d",
            "Nice products and timely delevary",
            "Cool and cline look and good workings",
            "Great Product",
            "Mind blowing",
            "Super product on price",
            "Good but..A little broken",
            "Pasting of stickeres quality is very poor. Compressor making heavy noise and looking very cheap",
            "Awesome product",
            "Nice \ud83d\ude0a",
            "Give me 1 pic more",
            "Good product and impressive and good quality in this price",
            "It's okay for small family but finishing is not likeable",
            "Good and great Onida refrigerator love it super \ud83e\udd17\ud83e\udd17\u2764\ufe0f\u2764\ufe0f\u2764\ufe0f\u2764\ufe0f\u2764\ufe0f\ud83c\udfe0",
            "Good product",
            "good compressor",
            "Ok",
            "Super cooling\nLoved it",
            "Good products",
            "Nice product.\nProduct is very good.\nQuality is excellent.\nThanks to flipkart....",
            "Nice good product",
            "Cheap quality product. Parts are very cheap and light.",
            "Good",
            "Good",
            "Awesome product",
            "Very good delivery and delivery boys are very good",
            "Nice product",
            "I complaint to flipkart the delivery & installation person are very very Bad habit due to they are not taken care during delivery , they are use like pick & throw ,\nBut , product is good for features and money I like this product.",
            "Good Onida product and profamanc very nice",
            "Very good product",
            "Nice product",
            "Good product value for money",
            "V. Good product.....",
            "He is very good and small",
            "Very nice",
            "Very nice product at very reasonable price.",
            "Value For Money",
            "Nice",
            "Best in the world in this price range",
            "The fridge is so beautiful and so stylish\nIt is so much better in this price you should buy it",
            "Nice",
            "Wow",
            "Refrigerator is good but the wire is very short.",
            "Nice",
            "Good",
            "Value for money",
            "Nice product\ndelivery super thank u",
            "Very nice....product",
            "Good",
            "Good product",
            "IT IS VERY GOOD AND FASTER",
            "Its a good one, 8 monts before purchased it\u2764\ufe0f",
            "flipkart service is very good they send products before its time and by the way onida refrigerator is very good by using",
            "Best option for lowest price",
            "Good for small family.",
            "nice product for couples and small family.\nFirst I have received this product as handle breaked . Next too many replacement requested next I have received the product as ok.",
            "Good fridge. Working good. Good fr a family of 3-4 people",
            "Very good",
            "Very comfortable for this price and product is very good, go for it to buy this product.",
            "Such a mind blowing in this range",
            "Very very good",
            "good",
            "Nice \ud83d\udc4d\ud83d\udc4d\ud83d\udc4d\ud83d\udc4d",
            "Nice",
            "Good",
            "I order for my friend family.. They was happy with it",
            "A good product",
            "good",
            "Good",
            "Nice product love it",
            "Awesome",
            "Good refrigerator",
            "Cooling is not properly work. Also come sealing from corner",
            "Full of ice in ice-cube box a big problem",
            "ok",
            "Perfect value for money",
            "Good in that budget",
            "Thanks",
            "Good",
            "Good Product \ud83e\udd70\ud83e\udd70\ud83e\udd70\ud83e\udd70\ud83e\udd70\ud83e\udd70\ud83e\udd70\ud83e\udd70\ud83e\udd70\ud83e\udd70\ud83e\udd70",
            "Milk tray is not good,quality also not good,price wise good.",
            "Mind-blowing purchase",
            "I am.so.happy and thanyou so.much flipkart customer care to.help.me",
            "Good & nice product",
            "Ok",
            "Nice \ud83d\udc4c\ud83d\udc4c",
            "Good",
            "Nice look",
            "Worst bro",
            "Very Good Product",
            "Disturb",
            "No operational\u2026worthless experience\u2026!!",
            "Very bed",
            "Malfunction product... doesn't work properly..takes lot of time for cooling.",
            "Ok ok product",
            "Not installation other then super",
            "Budget friendly",
            "Fantastic refrigerator",
            "Very nice fridge",
            "Made in india fridge and amazing in daily use",
            "Delivery be leted but, paching was very good ..\nGood service\nLove you filpikart ...",
            "Nice",
            "Amazing product",
            "VERY GOOD PRODUCT",
            "Ok nice",
            "No words to say just buy it",
            "Nice product , Good built quality , Value for Money , Nice Floral design looks nice , Nice delivery with full safety , Excellent Refrigerator .",
            "Nice",
            "Good product",
            "So good. But so small.",
            "Good product &good response...",
            "Excellent product ever",
            "Product is not so good but value for money at dis range.",
            "Value for money",
            "Excellent performance",
            "Nice frage thank you Flipkart",
            "Very nice",
            "Friger door not proper and back side copper will not fitting and cable will short . looking good",
            "Good for buy",
            "Very worst not worth for money .if I see pictures it shows big but am buy it it's very small .not satisfied",
            "Excellent for small family dont consider negative reviews... Just go for it",
            "Gud",
            "Nice",
            "Very happy \ud83d\ude01\ud83d\ude01\ud83d\ude01",
            "Good",
            "Good",
            "Good work",
            "Good product..",
            "Value you f money and you didnt accept this product but excellent",
            "Excellent product",
            "Good",
            "Really good brand and nice product. I use this product it is so fantastic outer and inner design is very good.",
            "Nice veri nice",
            "Super",
            "Too beautiful design & performance",
            "Overall best product value for money",
            "Nice product",
            "Nice one. I hope for good services.",
            "Product as per specification....nice",
            "Nice product",
            "Thnx so much it's an awesome",
            "Giving a little bit sound when it's started for cooling. Overall is a good product value for money. Looking is good",
            "Best buy at affordable price",
            "Hugr problem with defrosting system, freezer door got broke",
            "Item is as described & at best price...",
            "Good product",
            "Very good praduct .",
            "Good cooling system",
            "Highly recommended",
            "Too small in size",
            "Very useful to store vegetables",
            "Very nice",
            "Nice product",
            "Hi this refrigerator is very good",
            "Since 15 days of using good, no any problem",
            "Simply best product.. value for money..just go for it..",
            "Good",
            "More money more storage",
            "Nice super Onida fridge",
            "Value for money",
            "Ok\ud83d\udc4d\ud83d\udc4c",
            "Value for money",
            "It's says 190 litre but looks like 150 litre.. Similar capacity Whirlpool refrigerator is larger than this...",
            "Very nice",
            "Nice fantastic",
            "Good",
            "Good product thanks flipkart",
            "Recommended",
            "Good",
            "Electricity 171 unit par year",
            "Super ..fast cooling...\nWorth for money...\n\nDelivery ok..but service engineer not comming...\nNo response...\n\nOtherwise fride is excellent...",
            "Affordable product at this price",
            "I'm very happy to buy it.",
            "Super",
            "Nice one",
            "Good in that budget.\nHighly recommend",
            "Good working..but ice water leak",
            "Good",
            "Nice product and nice look",
            "super",
            "Exilent",
            "Gud",
            "Ice cubes are made very fast",
            "Good",
            "Nice",
            "It s ok",
            "Good",
            "Excellent.\nVery good product. Value for money",
            "Overall it is good. However finishing is not upto the mark and it makes noise as well. Noise is not very loud but still it makes.",
            "Good",
            "Good",
            "excellent",
            "Got in in a week after order. Looks fantastic.\nI will write more after using a week",
            "Very good product. Works like a charm. But delivery person was very unhelpful. He just put the fridge in my house and left, didn't answer any question, didn't help set it",
            "Fine....",
            "Good product",
            "Nice and excellent",
            "Value for money purchase.. Looks is good noise is less, chilling is avg .. Satisfying it's price",
            "Great fridge. Great service for one family.",
            "Very good",
            "Its making lot of noise....complained many times, but no response from flipkart...otherwise good",
            "This is great purchase for small family of 4.\n\ud83d\ude0a love it",
            "nice",
            "Good products",
            "Good",
            "Valuable",
            "Best courier service",
            "Very good",
            "Good product \ud83d\udc4d\ud83d\ude00",
            "Good",
            "It is great product, fool paisa vasool",
            "More than something what we know as BEST for 10450/-..\nPerfect for a family of 3-4. Perfectly serves the way as mentioned in the feature section. What's more!! Thanks.",
            "Compressor making a noise",
            "awesome product from when i got it has so much types of option also super saving mode this reduced your low eliectricity.",
            "Its ok not bad",
            "Excellent product in low price",
            "Very nice Product.... worth of money",
            "Just awesome \ud83d\ude0a",
            "Best in this range, loved it.",
            "Excellent product in this price range",
            "Awesome.",
            "Good",
            "Good product",
            "Just ok",
            "Nice",
            "Good",
            "Colour ,performance ,cooling evening perfect only issue ...plastic use in ice tray is not good and glass on fruit box is not fit.",
            "Best",
            "Ok,",
            "Damage pic's",
            "Super interior and nice refrigerator \ud83d\ude0d",
            "Good prodect",
            "Good product",
            "Nice thanks flipkart",
            "Nice product",
            "Good",
            "Nice product.thank you flipkar",
            "Verry nice",
            "Great.",
            "Good",
            "Very nice product..",
            "Simple Super",
            "Really awesome product.",
            "Excellent product.",
            "Good Refrigerator with this budget performance fridge same as other branded available in the market.",
            "Nice product",
            "Thankyou flipkart for ur valuable service & excellent product of course",
            "Worst product.. waste of money.. so many issues in this product..",
            "Very small",
            "Product came with a broken lock.",
            "Nice product",
            "Good",
            "It's a good product.. but just make a noise sometimes like Dharrrrrrrrrrrrr........... Over all Good",
            "West products don't parches",
            "Good product for small family thanks flipkart",
            "Superb products.. chills too fast.. ice making is decent.. also power efficient.",
            "Value of money & good product",
            "Nice classy Product with less \u2b50 \u2b50 \u2b50 Power consumption, Elegant Floral Design and exquisite Features in Good Affordable Price range . Ideal for Small Family... Much Happy and Highly Recommended for Purchase in Flipkart.. \ud83d\udc4c \ud83d\udc4f \ud83d\udc4d \ud83e\udd1d\ud83c\udffd \ud83d\udc90 \ud83d\ude4f",
            "Good at this price.",
            "So small in size",
            "Waste of money",
            "Super",
            "Bakwaas Product. Does not cool..",
            "Paisa wasool good product",
            "Sorry",
            "Worth for pricing",
            "Very nice",
            "Good for small family",
            "Very attractive in look and no issue as of now..bought it 2 weeks before so cant say precisely about performance",
            "Very good fridge",
            "Value for money",
            "For 2-3 persons only.",
            "VALUE FOR MONEY",
            "Good quality",
            "Worst product.",
            "Super bucket superrrrrrrr.",
            "Super",
            "Good product for this price, quality of the build is little lower.",
            "Nice product very good",
            "Making lot of noise",
            "Too noisey",
            "super",
            "Nice p",
            "I'm so happy",
            "Amazing",
            "superb product",
            "Fine quality",
            "Nice prodct delevari boys thanks to",
            "Good",
            "Good worth full product",
            "First impression is the best.\nVery stylish. Nice fit. Good for small family. Value for Money and last but not least fast delivery by Flipkart.",
            "Nice & good product,",
            "Noise coming.",
            "Good one",
            "Item is good but delivery is to late",
            "JJ gggy go h",
            "Nice ok*****",
            "Awesome product",
            "Perfect",
            "It's really good",
            "One month using after liting is not working",
            "Best is the ONIDA refrigerator...",
            "Nice",
            "Superb design. We can't get these kind of deals at regular shops. One of the best fridge at this price range. If your budet is around 10K then preferably this could be a great choice.",
            "Awesome product\ud83d\ude0a",
            "Very nice",
            "Good looking Refrigerator.nice making",
            "Ok",
            "Super cool",
            "It's the best refrigerator in this price range.",
            "It's value of money.\nDelivery on time.\nIt's a awesome product.",
            "Osm",
            "Very good products buy this products tension free",
            "Good product smooth use",
            "So far I like this refrigerator. It's been 10 Days I am using it.",
            "Just ok.\nThe material quality is very poor and weak.\nDoesnt have any weight on base, keep shaking while opening gate, internal accessories are also low grade acrylic.\nFor short term usage is ok",
            "Good product\nI am happy for buying",
            "Ok",
            "Gd",
            "Nice purchased in 9000",
            "Excellent product",
            "Very nice",
            "Nice product",
            "All good but lower of freezer means base not build in proper way.",
            "Good",
            "Product was very good.",
            "Amazing product.. budget friendly.. perfect for small family",
            "very good",
            "value for money",
            "It's very good",
            "I loved the product. \ud83d\udc4c",
            "Good cooling",
            "Very economic product",
            "I baught this product from flipcart last 3month ago product part are cheap and after 3 months use more noise.",
            "Very nice at this price",
            "One of Best products",
            "Just go for it",
            "Small",
            "super good product..sound is more",
            "Compressor make a lot of noise",
            "Beautiful",
            "Amazing",
            "Very nice",
            "THIS PRODUCT IS WELL AND BEST AS WELL THE THE SERVICE PROVIDED BY FLIPKART IS ALSO THE BEST.\nTHANKS, FLIPKART.",
            "Good delivery & service fast",
            "Good",
            "Nice",
            "Since and good working superb coolling",
            "Good",
            "You must buy this refrigerator, its awsome instant cooling.... good for 2 or 3 people....... i am happy for this product.. thanks flipcart",
            "Good",
            "Very good fridge. Top quality material. Satisfied.",
            "Nice design...and value for money",
            "Amazing product",
            "Bit short but good",
            "Superb",
            "Average refrigerator value for money",
            "Good product...",
            "Very Noise",
            "Expected better but it's ok",
            "Good product value for money and small family usage ok",
            "Condensation water drain tray kept to on top of compressor motor is not recommended need to see alternate location, quality of material not used entire unit need to improve",
            "Good Quality",
            "Value for money really I liked it.....",
            "So noise",
            "Overall good product with campare to price and electric consumption. But it make clunchy noise in freezing portion.",
            "Good power saver refrigerator in this price range and onida also big brand name I already using since last five days no complain but actual review after few months of using so presently running good",
            "Hello all its nice refrigerator for small family, cooling is good and size is also good, and you get what you paid, not expect for 10000 bucks quality like LG or Samsung, but surely value for money",
            "Ok ok .",
            "Recently o brought this one first door was struck layer when door was open its awesome it's working fine as of now value for money",
            "Nice fridge & fast cooling",
            "Very useful and delivery people are very helpful... Love u Ekart they will deliver to any place even it's a small village.. thank you\nComing to refrigerator\nIt is very useful for 3 to 4 people\nGood for small family\nInternal space is soo good and very clean.\nNo bad odur\nAs shown in the pics.\nColour is very nice and innovative.",
            "Body is not so strong as required. Always have a fear of breaking handle when pulling the door.",
            "Excellent.. Nice look.. value for money.. Working good but little small compare thn regular fridge other than can buy for small family",
            "Good",
            "Good for 3 or 4 people family.\nI really like it.\nValue for money.\nCheap and best.\nGood compressor.\nOverall good 10days review. Return period over yesterday.\nAm happy \u263a\ufe0f",
            "Very good product from onida\u2764\ufe0f\u2764\ufe0f\u2764\ufe0f",
            "Amazing",
            "It's key is not working",
            "Look wise is good it is small and compact but makes too much noise.",
            "Worth for money",
            "Awesome \ud83d\udc4d\ud83d\ude0e Product I'm happy with this \ud83d\udc4f",
            "not as looking ..size very small",
            "Nice beautiful",
            "Nice",
            "Some time it has minor noise but after some time it's be OK automatically .",
            "good",
            "This is a decent fridge but remember its direct cool so if one keeps it cooling high, water is seen in the fridge. It cools very fast and upto the mark.",
            "Osm",
            "Good product",
            "Interior material not so good,\nPlease don't buy",
            "Good for small family and no noise",
            "Good",
            "Super \ud83d\ude18 love it",
            "Beautiful design. Enough space. Good cooling. Easy maintenance.",
            "Its a nice product.. usable.",
            "Good",
            "I m still not much have ideas... How later it will work ... For now it's good enough",
            "Product is perfect for a small family ?",
            "Very good product",
            "I got it in 10990Rs . Overall performance is great. Good refrigerator",
            "Good good",
            "It's very good product",
            "Space problem",
            "Superb",
            "ok good",
            "Too small in size",
            "Superb \ud83d\udc4c\ud83d\udc4c\u2764\ufe0f\u2764\ufe0f",
            "Simply super",
            "Very good product",
            "My refrigerator is to much vapour in inside",
            "Value for money. The wiring at back is bit annoying.",
            "FINE CHEAP AND BEST..."
        ],
        "likes": [
            "228",
            "144",
            "15",
            "49",
            "1",
            "168",
            "376",
            "175",
            "82",
            "57",
            "228",
            "144",
            "15",
            "49",
            "1",
            "168",
            "376",
            "175",
            "82",
            "57",
            "84",
            "33",
            "8",
            "21",
            "18",
            "8",
            "12",
            "19",
            "44",
            "30",
            "6",
            "6",
            "18",
            "11",
            "25",
            "15",
            "5",
            "23",
            "21",
            "15",
            "7",
            "18",
            "16",
            "4",
            "3",
            "3",
            "3",
            "3",
            "7",
            "9",
            "9",
            "7",
            "3",
            "10",
            "8",
            "4",
            "5",
            "1",
            "1",
            "2",
            "2",
            "2",
            "2",
            "1",
            "2",
            "2",
            "6",
            "3",
            "2",
            "2",
            "2",
            "1",
            "1",
            "1",
            "1",
            "1",
            "1",
            "1",
            "1",
            "1",
            "0",
            "1",
            "0",
            "0",
            "0",
            "1",
            "1",
            "0",
            "0",
            "0",
            "1",
            "0",
            "1",
            "0",
            "1",
            "0",
            "1",
            "0",
            "1",
            "1",
            "1",
            "1",
            "0",
            "1",
            "1",
            "1",
            "1",
            "1",
            "1",
            "2",
            "1",
            "1",
            "0",
            "1",
            "1",
            "1",
            "1",
            "0",
            "1",
            "1",
            "1",
            "1",
            "1",
            "0",
            "0",
            "0",
            "0",
            "1",
            "0",
            "0",
            "0",
            "0",
            "0",
            "0",
            "0",
            "0",
            "0",
            "0",
            "0",
            "0",
            "0",
            "0",
            "0",
            "0",
            "0",
            "0",
            "0",
            "0",
            "0",
            "0",
            "0",
            "0",
            "0",
            "0",
            "0",
            "0",
            "0",
            "0",
            "0",
            "0",
            "0",
            "0",
            "0",
            "0",
            "0",
            "0",
            "0",
            "0",
            "0",
            "0",
            "0",
            "0",
            "0",
            "0",
            "0",
            "0",
            "0",
            "0",
            "0",
            "0",
            "0",
            "0",
            "0",
            "0",
            "0",
            "0",
            "0",
            "0",
            "1",
            "0",
            "0",
            "0",
            "0",
            "0",
            "0",
            "0",
            "0",
            "0",
            "0",
            "0",
            "0",
            "0",
            "0",
            "0",
            "0",
            "0",
            "0",
            "0",
            "0",
            "0",
            "0",
            "0",
            "0",
            "0",
            "0",
            "0",
            "0",
            "0",
            "0",
            "0",
            "0",
            "0",
            "0",
            "0",
            "0",
            "0",
            "0",
            "0",
            "0",
            "0",
            "0",
            "0",
            "0",
            "0",
            "0",
            "0",
            "0",
            "0",
            "0",
            "0",
            "0",
            "0",
            "0",
            "0",
            "0",
            "0",
            "0",
            "0",
            "0",
            "0",
            "0",
            "0",
            "0",
            "0",
            "0",
            "0",
            "0",
            "0",
            "0",
            "0",
            "0",
            "0",
            "0",
            "0",
            "0",
            "0",
            "0",
            "0",
            "0",
            "0",
            "0",
            "0",
            "0",
            "0",
            "0",
            "0",
            "0",
            "0",
            "0",
            "0",
            "0",
            "0",
            "0",
            "0",
            "0",
            "0",
            "0",
            "0",
            "0",
            "0",
            "0",
            "0",
            "0",
            "0",
            "0",
            "0",
            "0",
            "0",
            "0",
            "0",
            "0",
            "0",
            "0",
            "0",
            "0",
            "0",
            "0",
            "0",
            "0",
            "0",
            "0",
            "0",
            "0",
            "0",
            "0",
            "0",
            "0",
            "1",
            "0",
            "0",
            "0",
            "0",
            "0",
            "0",
            "0",
            "0",
            "0",
            "0",
            "0",
            "0",
            "0",
            "0",
            "0",
            "0",
            "0",
            "0",
            "0",
            "0",
            "0",
            "0",
            "0",
            "0",
            "0",
            "0",
            "0",
            "0",
            "0",
            "0",
            "0",
            "0",
            "0",
            "0",
            "0",
            "0",
            "0",
            "0",
            "0",
            "0",
            "0",
            "0",
            "0",
            "0",
            "0",
            "0",
            "0",
            "0",
            "0",
            "0",
            "0",
            "0",
            "0",
            "0",
            "0",
            "0",
            "0",
            "0",
            "0",
            "0",
            "0",
            "0",
            "0",
            "0",
            "0",
            "0",
            "0",
            "0",
            "0",
            "0",
            "0",
            "0",
            "0",
            "0",
            "0",
            "0",
            "0",
            "0",
            "0",
            "0",
            "0",
            "0",
            "0",
            "0",
            "0",
            "0",
            "0",
            "0",
            "0",
            "0",
            "0",
            "0",
            "0",
            "0",
            "0",
            "0",
            "0",
            "0",
            "0",
            "0",
            "0",
            "0",
            "0",
            "0",
            "0",
            "0",
            "0",
            "0",
            "0",
            "0",
            "0",
            "0",
            "0",
            "0",
            "0",
            "0",
            "0",
            "0",
            "0",
            "0",
            "0",
            "0",
            "0",
            "0",
            "0",
            "0",
            "0",
            "0",
            "0",
            "0",
            "0",
            "0",
            "0",
            "0",
            "0",
            "0",
            "0",
            "0",
            "0",
            "0",
            "0",
            "0",
            "0",
            "0",
            "0",
            "0",
            "0",
            "0",
            "0",
            "0",
            "0",
            "0",
            "0",
            "0",
            "0",
            "0",
            "0",
            "0",
            "0",
            "0",
            "0",
            "0",
            "0",
            "0",
            "0",
            "2",
            "0",
            "0",
            "0",
            "0",
            "0",
            "0",
            "0",
            "0",
            "0",
            "0",
            "0",
            "0",
            "0",
            "0",
            "0",
            "0",
            "0",
            "0",
            "0",
            "0",
            "0",
            "0",
            "0",
            "0",
            "1",
            "0",
            "0",
            "0",
            "0",
            "0",
            "0",
            "0",
            "0",
            "0",
            "0",
            "0",
            "0",
            "0",
            "0",
            "0",
            "0",
            "0",
            "0",
            "0",
            "0",
            "0",
            "0",
            "0",
            "0",
            "0",
            "0",
            "0",
            "0",
            "0",
            "0",
            "0",
            "0",
            "0",
            "0",
            "0",
            "0",
            "0",
            "0",
            "0",
            "0",
            "0",
            "0",
            "0",
            "0",
            "0",
            "0",
            "0",
            "0",
            "0",
            "0",
            "0",
            "0",
            "0",
            "0",
            "0",
            "0",
            "0",
            "0",
            "0",
            "0",
            "0",
            "0",
            "0",
            "0",
            "0",
            "0",
            "0",
            "0",
            "0",
            "0",
            "0",
            "0",
            "0",
            "0",
            "0",
            "0",
            "0",
            "0",
            "0",
            "0",
            "0",
            "0",
            "0",
            "0",
            "0",
            "0",
            "0",
            "0",
            "0",
            "0",
            "0",
            "0",
            "0",
            "0",
            "0",
            "0",
            "0",
            "0",
            "0",
            "0",
            "0",
            "0",
            "0",
            "0",
            "0",
            "0",
            "0",
            "0",
            "0",
            "0",
            "0",
            "0",
            "0",
            "0",
            "0",
            "0",
            "0",
            "0",
            "0",
            "0",
            "0",
            "0",
            "0",
            "0",
            "0",
            "0",
            "0",
            "0",
            "0",
            "0",
            "0",
            "0",
            "0",
            "0",
            "0",
            "0",
            "0",
            "0",
            "0",
            "0",
            "0",
            "0",
            "0",
            "0",
            "0",
            "0",
            "0",
            "0",
            "0",
            "0",
            "0",
            "0",
            "0",
            "0",
            "0",
            "0",
            "0",
            "0",
            "0",
            "0",
            "0",
            "0",
            "0",
            "0",
            "0",
            "0",
            "0",
            "0",
            "0",
            "0",
            "0",
            "0",
            "0",
            "0",
            "0",
            "0",
            "0",
            "0",
            "0",
            "0",
            "0",
            "0",
            "0",
            "0",
            "0",
            "0",
            "0",
            "0",
            "0",
            "0",
            "0",
            "0",
            "0",
            "0"
        ],
        "dislikes": [
            "65",
            "74",
            "2",
            "29",
            "0",
            "22",
            "77",
            "29",
            "12",
            "9",
            "65",
            "74",
            "2",
            "29",
            "0",
            "22",
            "77",
            "29",
            "12",
            "9",
            "16",
            "6",
            "0",
            "3",
            "2",
            "0",
            "1",
            "3",
            "12",
            "8",
            "0",
            "0",
            "5",
            "2",
            "9",
            "4",
            "0",
            "10",
            "9",
            "5",
            "1",
            "7",
            "6",
            "0",
            "0",
            "0",
            "0",
            "0",
            "2",
            "4",
            "4",
            "2",
            "0",
            "5",
            "4",
            "1",
            "2",
            "0",
            "0",
            "0",
            "0",
            "0",
            "0",
            "0",
            "0",
            "0",
            "4",
            "1",
            "2",
            "1",
            "1",
            "0",
            "0",
            "0",
            "0",
            "0",
            "0",
            "0",
            "0",
            "0",
            "0",
            "0",
            "0",
            "0",
            "0",
            "0",
            "0",
            "0",
            "0",
            "0",
            "0",
            "0",
            "0",
            "0",
            "0",
            "0",
            "0",
            "0",
            "0",
            "0",
            "0",
            "0",
            "0",
            "0",
            "0",
            "0",
            "0",
            "0",
            "0",
            "1",
            "0",
            "0",
            "1",
            "2",
            "1",
            "1",
            "1",
            "1",
            "1",
            "1",
            "1",
            "1",
            "1",
            "0",
            "0",
            "0",
            "0",
            "0",
            "0",
            "0",
            "0",
            "0",
            "0",
            "0",
            "0",
            "0",
            "0",
            "0",
            "0",
            "0",
            "0",
            "0",
            "0",
            "0",
            "0",
            "0",
            "0",
            "0",
            "0",
            "0",
            "0",
            "0",
            "0",
            "0",
            "0",
            "0",
            "0",
            "0",
            "0",
            "0",
            "0",
            "0",
            "0",
            "0",
            "0",
            "0",
            "0",
            "0",
            "0",
            "0",
            "0",
            "0",
            "0",
            "0",
            "0",
            "0",
            "0",
            "0",
            "0",
            "0",
            "0",
            "0",
            "0",
            "0",
            "0",
            "0",
            "0",
            "0",
            "0",
            "0",
            "0",
            "0",
            "0",
            "0",
            "0",
            "0",
            "0",
            "0",
            "0",
            "0",
            "0",
            "0",
            "0",
            "0",
            "0",
            "0",
            "0",
            "0",
            "0",
            "0",
            "0",
            "0",
            "0",
            "0",
            "0",
            "0",
            "0",
            "0",
            "0",
            "0",
            "0",
            "0",
            "0",
            "0",
            "0",
            "0",
            "0",
            "0",
            "0",
            "0",
            "0",
            "0",
            "0",
            "0",
            "0",
            "0",
            "0",
            "0",
            "0",
            "0",
            "0",
            "0",
            "0",
            "0",
            "0",
            "0",
            "0",
            "0",
            "0",
            "0",
            "0",
            "0",
            "0",
            "0",
            "0",
            "0",
            "0",
            "0",
            "0",
            "0",
            "0",
            "0",
            "0",
            "0",
            "0",
            "0",
            "0",
            "0",
            "0",
            "0",
            "0",
            "0",
            "0",
            "0",
            "0",
            "0",
            "0",
            "0",
            "0",
            "0",
            "0",
            "0",
            "0",
            "0",
            "0",
            "0",
            "0",
            "0",
            "0",
            "0",
            "0",
            "0",
            "0",
            "0",
            "0",
            "0",
            "0",
            "0",
            "0",
            "0",
            "0",
            "0",
            "0",
            "0",
            "0",
            "0",
            "0",
            "0",
            "0",
            "0",
            "0",
            "1",
            "0",
            "0",
            "0",
            "0",
            "0",
            "1",
            "0",
            "0",
            "0",
            "0",
            "0",
            "0",
            "0",
            "0",
            "0",
            "0",
            "0",
            "0",
            "0",
            "0",
            "0",
            "0",
            "0",
            "0",
            "0",
            "0",
            "0",
            "0",
            "0",
            "0",
            "1",
            "0",
            "0",
            "0",
            "0",
            "0",
            "0",
            "0",
            "0",
            "0",
            "0",
            "0",
            "0",
            "0",
            "0",
            "0",
            "0",
            "0",
            "0",
            "0",
            "0",
            "0",
            "0",
            "0",
            "0",
            "0",
            "0",
            "0",
            "0",
            "0",
            "0",
            "0",
            "0",
            "0",
            "0",
            "0",
            "0",
            "0",
            "0",
            "0",
            "0",
            "0",
            "0",
            "0",
            "0",
            "0",
            "0",
            "0",
            "0",
            "0",
            "0",
            "0",
            "0",
            "0",
            "0",
            "0",
            "0",
            "0",
            "0",
            "0",
            "0",
            "0",
            "0",
            "0",
            "0",
            "0",
            "0",
            "0",
            "0",
            "0",
            "0",
            "0",
            "0",
            "0",
            "0",
            "0",
            "0",
            "0",
            "0",
            "0",
            "0",
            "0",
            "0",
            "0",
            "0",
            "0",
            "0",
            "0",
            "0",
            "0",
            "0",
            "0",
            "0",
            "0",
            "0",
            "0",
            "0",
            "0",
            "0",
            "0",
            "0",
            "0",
            "1",
            "0",
            "0",
            "0",
            "0",
            "0",
            "0",
            "0",
            "0",
            "0",
            "0",
            "0",
            "0",
            "0",
            "0",
            "0",
            "0",
            "0",
            "0",
            "0",
            "0",
            "0",
            "0",
            "0",
            "0",
            "0",
            "0",
            "0",
            "0",
            "0",
            "0",
            "0",
            "0",
            "0",
            "0",
            "0",
            "0",
            "0",
            "0",
            "0",
            "0",
            "0",
            "0",
            "0",
            "0",
            "0",
            "0",
            "0",
            "0",
            "0",
            "0",
            "0",
            "0",
            "0",
            "0",
            "0",
            "0",
            "0",
            "0",
            "0",
            "0",
            "0",
            "0",
            "0",
            "0",
            "0",
            "0",
            "0",
            "0",
            "0",
            "0",
            "0",
            "0",
            "0",
            "0",
            "0",
            "0",
            "0",
            "0",
            "0",
            "0",
            "0",
            "0",
            "0",
            "0",
            "0",
            "0",
            "0",
            "0",
            "0",
            "0",
            "0",
            "0",
            "0",
            "0",
            "0",
            "0",
            "0",
            "0",
            "1",
            "0",
            "0",
            "0",
            "0",
            "0",
            "0",
            "0",
            "0",
            "0",
            "0",
            "0",
            "0",
            "0",
            "0",
            "0",
            "0",
            "0",
            "0",
            "0",
            "0",
            "0",
            "0",
            "0",
            "0",
            "0",
            "0",
            "0",
            "0",
            "0",
            "0",
            "0",
            "0",
            "0",
            "0",
            "0",
            "0",
            "0",
            "0",
            "0",
            "0",
            "0",
            "0",
            "0",
            "0",
            "0",
            "0",
            "0",
            "0",
            "0",
            "0",
            "0",
            "0",
            "0",
            "0",
            "0",
            "0",
            "0",
            "0",
            "0",
            "0",
            "0",
            "0",
            "0",
            "0",
            "0",
            "0",
            "0",
            "0",
            "0",
            "0",
            "0",
            "0",
            "0",
            "0",
            "0",
            "0",
            "0",
            "0",
            "0",
            "0",
            "0",
            "0",
            "0",
            "2",
            "0",
            "0",
            "0",
            "0",
            "0",
            "0",
            "0",
            "0",
            "0",
            "0",
            "0",
            "0",
            "0",
            "0",
            "0",
            "0",
            "0",
            "0",
            "0",
            "0",
            "0",
            "0",
            "0",
            "0",
            "0",
            "0",
            "0",
            "0",
            "0",
            "0",
            "0",
            "0",
            "0",
            "0",
            "0",
            "0",
            "0",
            "0",
            "0",
            "0",
            "0",
            "0",
            "0",
            "0",
            "0",
            "0",
            "0",
            "0",
            "0",
            "0",
            "0",
            "0",
            "0",
            "0",
            "0",
            "0",
            "0",
            "0",
            "0",
            "0",
            "0",
            "0",
            "0",
            "0",
            "0",
            "0",
            "0",
            "0",
            "0",
            "0",
            "0",
            "0",
            "0",
            "0",
            "1"
        ]
    },
    "qna": {
        "questions": [
            "Q:this fridge required stabilizer",
            "Q:Is it mandatory for stablizer",
            "Q:how many units per year?",
            "Q:I have bought this,the refrigerator is making noise is it normal or it's a problem?",
            "Q:Wheel support yes or no",
            "Q:Monthly average electricity consumption in units?",
            "Q:Without stabilier use this refrigerater",
            "Q:What about sound",
            "Q:how many litres this refrigerator",
            "Q:Does it need stabilizer?",
            "Q:It is freeze .plz suggust me in this freeze",
            "Q:Where will b the key present....I am not able to open the fridge...plz do help",
            "Q:is it required stabilizer or not? in description it's mentioned not having inbuilt stabilizer.",
            "Q:does this fridge need stabilizer ?",
            "Q:its height fridge",
            "Q:Those it make noise ...or sound",
            "Q:What's the height of refrigerator?",
            "Q:Can I make Ice cream",
            "Q:Is it of LG company",
            "Q:What is the colour",
            "Q:Does the stup require a professional to come in or can I just plug it in and start using the fridge?",
            "Q:Is this fridge required stabliger",
            "Q:It have any stibiliser",
            "Q:Can this automatically",
            "Q:Does it have manual defrost button?",
            "Q:Is this inverter compressor",
            "Q:Is that fridge comes with stand?",
            "Q:Is there any dent on the compressor?",
            "Q:it have stand?",
            "Q:does it have defrost tray",
            "Q:after cnotinuos on for 2 to 3 hours,how many hours can be chill",
            "Q:Onion tray bottom in this",
            "Q:The b is cover or not",
            "Q:Which company compresser are used",
            "Q:does this fridge have ice & egg tray and lock & key??",
            "Q:use this product without stabliser",
            "Q:what about its height",
            "Q:How many Watts electricity consumption this refrigerator",
            "Q:what comes with fridge?",
            "Q:in this fridge is there any light bulb or not.?",
            "Q:How many unit it consumes yearly?",
            "Q:Without stabilizer it's good?",
            "Q:extra stabilizer required? After Power cut what is the status of cooling retention?",
            "Q:Is this product heat problem",
            "Q:in built stabilizer present or not ?",
            "Q:Ice lock available or not ??",
            "Q:Junction box connect with refrigerator possible have any issues",
            "Q:Does this refrigerator needs external stabilizer?",
            "Q:With stabiliser yes or no",
            "Q:I can useing without stebliser?",
            "Q:The putting parts are of plastic or glass plzz reply",
            "Q:how many hieght the fridge is"
        ],
        "answers": [
            "A:Yes... I buy this refizaretor & just 2 days gon, the fridge is not cooling, now visit the technician & said this fridge required stabilizer..",
            "A:Yes",
            "A:70 units",
            "A:normal",
            "A:no",
            "A:14.25 units according to the label on the product.",
            "A:yes off course \ud83d\udc4d",
            "A:Best products high speed Colling thanks to flipkart",
            "A:190 Liters",
            "A:no",
            "A:yes",
            "A:The key and the booklet was seen pasted with the ice tray, enclosed in a packet.",
            "A:Better use with stablizer",
            "A:yes",
            "A:4ft",
            "A:No... Runs Smoothly",
            "A:Approximately 3 ft 6 inch",
            "A:no",
            "A:No",
            "A:shiny blue",
            "A:you have to set up by yourself",
            "A:no",
            "A:no",
            "A:no",
            "A:yes,u can seen when door open.",
            "A:No",
            "A:no",
            "A:Yes",
            "A:No.....refrigerator without stand",
            "A:yes",
            "A:2",
            "A:yes",
            "A:not.",
            "A:reciprocating compressor",
            "A:yes",
            "A:Yes u can",
            "A:Approx 5 feet",
            "A:Approximately 110 units ( watts) in 2 months.",
            "A:One packaging box and some thermacol",
            "A:Yes, in this fridge LED bulb lower level of defridge.",
            "A:171 unit per year as per BEE 2020",
            "A:good",
            "A:voltage 190 up refrigerator work properly ,190 voltage Down your area stabilizer required refrigerator",
            "A:no.",
            "A:Not",
            "A:available",
            "A:No",
            "A:No",
            "A:no",
            "A:Yes",
            "A:water self is plastic and fridge rack is glass",
            "A:4"
        ],
        "likes": [
            "29",
            "28",
            "107",
            "2",
            "3",
            "3",
            "3",
            "3",
            "3",
            "4",
            "2",
            "2",
            "1",
            "6",
            "1",
            "2",
            "2",
            "0",
            "0",
            "0",
            "1",
            "1",
            "0",
            "1",
            "0",
            "1",
            "0",
            "0",
            "1",
            "0",
            "0",
            "1",
            "0",
            "1",
            "55",
            "97",
            "61",
            "8",
            "34",
            "3",
            "2",
            "4",
            "3",
            "3",
            "2",
            "0",
            "0",
            "0",
            "0",
            "1",
            "0",
            "1"
        ],
        "dislikes": [
            "4",
            "5",
            "48",
            "0",
            "0",
            "0",
            "0",
            "0",
            "0",
            "2",
            "0",
            "0",
            "1",
            "7",
            "2",
            "3",
            "3",
            "0",
            "0",
            "0",
            "0",
            "0",
            "0",
            "0",
            "1",
            "0",
            "0",
            "0",
            "0",
            "2",
            "1",
            "1",
            "3",
            "0",
            "16",
            "34",
            "30",
            "1",
            "19",
            "0",
            "0",
            "2",
            "2",
            "1",
            "4",
            "0",
            "0",
            "0",
            "0",
            "0",
            "1",
            "0"
        ]
    }
}